MANIFEST.in
README.rst
requirements.txt
setup.py
debugmail/__init__.py
debugmail/backends.py
django_debugmail.egg-info/PKG-INFO
django_debugmail.egg-info/SOURCES.txt
django_debugmail.egg-info/dependency_links.txt
django_debugmail.egg-info/not-zip-safe
django_debugmail.egg-info/requires.txt
django_debugmail.egg-info/top_level.txt