Metadata-Version: 1.1
Name: django-debugmail
Version: 1.0.4
Summary: Debug based e-mail backend.
Home-page: https://github.com/radiosilence/django-debugmail.git
Author: James Cleveland
Author-email: jc@blackflags.co.uk
License: UNKNOWN
Platform: UNKNOWN
Classifier: Environment :: Web Environment
Classifier: Intended Audience :: Developers
Classifier: License :: OSI Approved :: BSD License
Classifier: Operating System :: OS Independent
Classifier: Programming Language :: Python
Classifier: Framework :: Django
